cutecare
