Metadata-Version: 1.1
Name: cutecare-py
Version: 0.16
Summary: Library to read data from CuteCare Bluetooth LE DIY sensor
Home-page: https://github.com/cutecare/cutecare-py
Author: Evgeny Savitsky
Author-email: evgeny.savitsky@gmail.com
License: MIT
Keywords: home assistant sensor bluetooth low-energy ble
Platform: UNKNOWN
Classifier: Development Status :: 3 - Alpha
Classifier: Intended Audience :: Developers
Classifier: Topic :: System :: Hardware :: Hardware Drivers
Classifier: License :: OSI Approved :: MIT License
Classifier: Programming Language :: Python :: 3
Classifier: Programming Language :: Python :: 3.4
Classifier: Programming Language :: Python :: 3.5
